spylls/__init__.py
spylls/hunspell/__init__.py
spylls/hunspell/dictionary.py
spylls/hunspell/algo/__init__.py
spylls/hunspell/algo/capitalization.py
spylls/hunspell/algo/lookup.py
spylls/hunspell/algo/ngram_suggest.py
spylls/hunspell/algo/permutations.py
spylls/hunspell/algo/phonet_suggest.py
spylls/hunspell/algo/string_metrics.py
spylls/hunspell/algo/suggest.py
spylls/hunspell/algo/trie.py
spylls/hunspell/data/__init__.py
spylls/hunspell/data/aff.py
spylls/hunspell/data/dic.py
spylls/hunspell/data/en/en_US.aff
spylls/hunspell/data/en/en_US.dic
spylls/hunspell/data/ru/ru.aff
spylls/hunspell/data/ru/ru.dic
spylls/hunspell/data/sv/sv_SE.aff
spylls/hunspell/data/sv/sv_SE.dic
spylls/hunspell/readers/__init__.py
spylls/hunspell/readers/aff.py
spylls/hunspell/readers/dic.py
spylls/hunspell/readers/file_reader.py
tests/__init__.py
tests/test_spyll.py
spylls-0.1.7.dist-info/LICENSE
spylls-0.1.7.dist-info/METADATA
spylls-0.1.7.dist-info/WHEEL
spylls-0.1.7.dist-info/top_level.txt
spylls-0.1.7.dist-info/RECORD
