Metadata-Version: 2.1
Name: spylls
Version: 0.1.7
Summary: Hunspell ported to pure Python
Home-page: https://github.com/zverok/spylls
Author: Victor Shepelev
Author-email: zverok.offline@gmail.com
License: UNKNOWN
Keywords: hunspell,spelling,spellcheck,suggest
Platform: UNKNOWN
Classifier: Development Status :: 4 - Beta
Classifier: Intended Audience :: Developers
Classifier: Intended Audience :: Science/Research
Classifier: License :: OSI Approved :: MIT License
Classifier: Programming Language :: Python :: 3.7
Classifier: Programming Language :: Python :: 3.8
Classifier: Programming Language :: Python :: 3.9
Classifier: Operating System :: OS Independent
Classifier: Topic :: Text Processing :: Linguistic
Requires-Python: >=3.7
